pyttd/__init__.py
pyttd/client.py
pyttd/py.typed
pyttd/game/__init__.py
pyttd/game/commands.py
pyttd/game/game_state.py
pyttd/network/__init__.py
pyttd/network/protocol.py
pyttd/saveload/__init__.py
pyttd/saveload/company_names.py
pyttd/saveload/exporter.py
pyttd/saveload/formatter.py
pyttd/saveload/map_flatbuffers.py
pyttd/saveload/models.py
pyttd/saveload/parser.py
pyttd/saveload/reader.py
pyttd/saveload/tiles.py
pyttd-1.3.0.dist-info/licenses/LICENSE
pyttd-1.3.0.dist-info/METADATA
pyttd-1.3.0.dist-info/WHEEL
pyttd-1.3.0.dist-info/entry_points.txt
pyttd-1.3.0.dist-info/top_level.txt
pyttd-1.3.0.dist-info/RECORD
