Metadata-Version: 2.4
Name: pyttd
Version: 1.3.0
Summary: OpenTTD Client Library
Home-page: https://github.com/mssc89/pyttd
Author: mssc89
Author-email: mssc89 <pyttd@example.com>
License: MIT
Project-URL: Homepage, https://github.com/mssc89/pyttd
Project-URL: Bug Tracker, https://github.com/mssc89/pyttd/issues
Project-URL: Documentation, https://github.com/mssc89/pyttd#readme
Project-URL: Source Code, https://github.com/mssc89/pyttd
Keywords: openttd,transport,tycoon,simulation,game,ai,bot,client,network,protocol,multiplayer,automation
Classifier: Development Status :: 5 - Production/Stable
Classifier: Intended Audience :: Developers
Classifier: License :: OSI Approved :: MIT License
Classifier: Operating System :: OS Independent
Classifier: Programming Language :: Python :: 3
Classifier: Programming Language :: Python :: 3.11
Classifier: Programming Language :: Python :: 3.12
Classifier: Topic :: Games/Entertainment :: Simulation
Classifier: Topic :: Software Development :: Libraries :: Python Modules
Classifier: Topic :: Internet :: WWW/HTTP :: HTTP Servers
Classifier: Topic :: System :: Networking
Requires-Python: >=3.11
License-File: LICENSE
Requires-Dist: flatbuffers>=24.3.25
Provides-Extra: dev
Requires-Dist: pytest>=6.0; extra == "dev"
Requires-Dist: pytest-cov>=2.0; extra == "dev"
Requires-Dist: black>=21.0; extra == "dev"
Requires-Dist: flake8>=3.8; extra == "dev"
Requires-Dist: mypy>=0.900; extra == "dev"
Provides-Extra: examples
Requires-Dist: colorama>=0.4.4; extra == "examples"
Dynamic: author
Dynamic: home-page
Dynamic: license-file
Dynamic: requires-python
